inertia/__init__.py
inertia/config.py
inertia/exceptions.py
inertia/inertia.py
inertia/py.typed
inertia/templating.py
inertia/utils.py
fastapi_inertia-1.1.0.dist-info/LICENSE
fastapi_inertia-1.1.0.dist-info/METADATA
fastapi_inertia-1.1.0.dist-info/WHEEL
fastapi_inertia-1.1.0.dist-info/RECORD
