Metadata-Version: 2.3
Name: fastapi-inertia
Version: 1.1.0
Summary: An implementation of the Inertia protocol for FastAPI.
License: MIT
Keywords: inertia,inertiajs,fastapi,python
Author: Hugo Mortreux
Author-email: 70602545+hxjo@users.noreply.github.com
Requires-Python: >=3.9
Classifier: Framework :: FastAPI
Classifier: License :: OSI Approved :: MIT License
Classifier: Operating System :: OS Independent
Classifier: Programming Language :: Python :: 3
Classifier: Programming Language :: Python :: 3.9
Classifier: Programming Language :: Python :: 3.10
Classifier: Programming Language :: Python :: 3.11
Classifier: Programming Language :: Python :: 3.12
Classifier: Programming Language :: Python :: 3.13
Classifier: Topic :: Software Development :: Libraries :: Python Modules
Requires-Dist: fastapi (>=0.111.0)
Requires-Dist: jinja2 (>=3.1.4)
Project-URL: Homepage, https://github.com/hxjo/fastapi-inertia
Project-URL: Repository, https://github.com/hxjo/fastapi-inertia
